{"nodes": [{"id": "users_morriz_workspace_morriz_itsup_agents_master_md", "label": "AGENTS.master.md", "file_type": "document", "source_file": "AGENTS.master.md", "source_location": "L1"}, {"id": "itsup_agents_master_developer_guide_concise_complete", "label": "Developer Guide (concise, complete)", "file_type": "document", "source_file": "AGENTS.master.md", "source_location": "L1"}, {"id": "itsup_agents_master_critical_rules", "label": "Critical Rules", "file_type": "document", "source_file": "AGENTS.master.md", "source_location": "L5"}, {"id": "itsup_agents_master_formatting_linting_tests_pre_commit_order", "label": "Formatting, Linting, Tests (pre-commit order)", "file_type": "document", "source_file": "AGENTS.master.md", "source_location": "L12"}, {"id": "itsup_agents_master_python_naming", "label": "Python Naming", "file_type": "document", "source_file": "AGENTS.master.md", "source_location": "L21"}, {"id": "itsup_agents_master_setup_installation", "label": "Setup & Installation", "file_type": "document", "source_file": "AGENTS.master.md", "source_location": "L26"}, {"id": "itsup_agents_master_deploy_orchestration", "label": "Deploy / Orchestration", "file_type": "document", "source_file": "AGENTS.master.md", "source_location": "L32"}, {"id": "itsup_agents_master_stack_commands", "label": "Stack Commands", "file_type": "document", "source_file": "AGENTS.master.md", "source_location": "L38"}, {"id": "itsup_agents_master_project_service_ops", "label": "Project Service Ops", "file_type": "document", "source_file": "AGENTS.master.md", "source_location": "L44"}, {"id": "itsup_agents_master_make_dev_tools_only_runtime_uses_itsup", "label": "Make (dev tools only; runtime uses itsup)", "file_type": "document", "source_file": "AGENTS.master.md", "source_location": "L50"}, {"id": "itsup_agents_master_artifact_generation", "label": "Artifact Generation", "file_type": "document", "source_file": "AGENTS.master.md", "source_location": "L55"}, {"id": "itsup_agents_master_utilities", "label": "Utilities", "file_type": "document", "source_file": "AGENTS.master.md", "source_location": "L60"}, {"id": "itsup_agents_master_all_itsup_commands", "label": "All itsup commands", "file_type": "document", "source_file": "AGENTS.master.md", "source_location": "L66"}, {"id": "itsup_agents_master_testing_always_test_after_changes", "label": "Testing (always test after changes!)", "file_type": "document", "source_file": "AGENTS.master.md", "source_location": "L70"}, {"id": "itsup_agents_master_v2_architecture_patterns", "label": "V2 Architecture Patterns", "file_type": "document", "source_file": "AGENTS.master.md", "source_location": "L76"}, {"id": "itsup_agents_master_containerization_scope", "label": "Containerization Scope", "file_type": "document", "source_file": "AGENTS.master.md", "source_location": "L98"}, {"id": "itsup_agents_master_code_standards", "label": "Code Standards", "file_type": "document", "source_file": "AGENTS.master.md", "source_location": "L103"}, {"id": "itsup_agents_master_testing_standards", "label": "Testing Standards", "file_type": "document", "source_file": "AGENTS.master.md", "source_location": "L107"}], "edges": [{"source": "users_morriz_workspace_morriz_itsup_agents_master_md", "target": "itsup_agents_master_developer_guide_concise_complete", "relation": "contains", "confidence": "EXTRACTED", "source_file": "AGENTS.master.md", "source_location": "L1", "weight": 1.0}, {"source": "itsup_agents_master_developer_guide_concise_complete", "target": "itsup_agents_master_critical_rules", "relation": "contains", "confidence": "EXTRACTED", "source_file": "AGENTS.master.md", "source_location": "L5", "weight": 1.0}, {"source": "itsup_agents_master_developer_guide_concise_complete", "target": "itsup_agents_master_formatting_linting_tests_pre_commit_order", "relation": "contains", "confidence": "EXTRACTED", "source_file": "AGENTS.master.md", "source_location": "L12", "weight": 1.0}, {"source": "itsup_agents_master_developer_guide_concise_complete", "target": "itsup_agents_master_python_naming", "relation": "contains", "confidence": "EXTRACTED", "source_file": "AGENTS.master.md", "source_location": "L21", "weight": 1.0}, {"source": "itsup_agents_master_developer_guide_concise_complete", "target": "itsup_agents_master_setup_installation", "relation": "contains", "confidence": "EXTRACTED", "source_file": "AGENTS.master.md", "source_location": "L26", "weight": 1.0}, {"source": "itsup_agents_master_developer_guide_concise_complete", "target": "itsup_agents_master_deploy_orchestration", "relation": "contains", "confidence": "EXTRACTED", "source_file": "AGENTS.master.md", "source_location": "L32", "weight": 1.0}, {"source": "itsup_agents_master_developer_guide_concise_complete", "target": "itsup_agents_master_stack_commands", "relation": "contains", "confidence": "EXTRACTED", "source_file": "AGENTS.master.md", "source_location": "L38", "weight": 1.0}, {"source": "itsup_agents_master_developer_guide_concise_complete", "target": "itsup_agents_master_project_service_ops", "relation": "contains", "confidence": "EXTRACTED", "source_file": "AGENTS.master.md", "source_location": "L44", "weight": 1.0}, {"source": "itsup_agents_master_developer_guide_concise_complete", "target": "itsup_agents_master_make_dev_tools_only_runtime_uses_itsup", "relation": "contains", "confidence": "EXTRACTED", "source_file": "AGENTS.master.md", "source_location": "L50", "weight": 1.0}, {"source": "itsup_agents_master_developer_guide_concise_complete", "target": "itsup_agents_master_artifact_generation", "relation": "contains", "confidence": "EXTRACTED", "source_file": "AGENTS.master.md", "source_location": "L55", "weight": 1.0}, {"source": "itsup_agents_master_developer_guide_concise_complete", "target": "itsup_agents_master_utilities", "relation": "contains", "confidence": "EXTRACTED", "source_file": "AGENTS.master.md", "source_location": "L60", "weight": 1.0}, {"source": "itsup_agents_master_utilities", "target": "itsup_agents_master_all_itsup_commands", "relation": "contains", "confidence": "EXTRACTED", "source_file": "AGENTS.master.md", "source_location": "L66", "weight": 1.0}, {"source": "itsup_agents_master_developer_guide_concise_complete", "target": "itsup_agents_master_testing_always_test_after_changes", "relation": "contains", "confidence": "EXTRACTED", "source_file": "AGENTS.master.md", "source_location": "L70", "weight": 1.0}, {"source": "itsup_agents_master_developer_guide_concise_complete", "target": "itsup_agents_master_v2_architecture_patterns", "relation": "contains", "confidence": "EXTRACTED", "source_file": "AGENTS.master.md", "source_location": "L76", "weight": 1.0}, {"source": "itsup_agents_master_developer_guide_concise_complete", "target": "itsup_agents_master_containerization_scope", "relation": "contains", "confidence": "EXTRACTED", "source_file": "AGENTS.master.md", "source_location": "L98", "weight": 1.0}, {"source": "itsup_agents_master_developer_guide_concise_complete", "target": "itsup_agents_master_code_standards", "relation": "contains", "confidence": "EXTRACTED", "source_file": "AGENTS.master.md", "source_location": "L103", "weight": 1.0}, {"source": "itsup_agents_master_developer_guide_concise_complete", "target": "itsup_agents_master_testing_standards", "relation": "contains", "confidence": "EXTRACTED", "source_file": "AGENTS.master.md", "source_location": "L107", "weight": 1.0}], "input_tokens": 0, "output_tokens": 0}